{"credit":"Made with Blockbench","textures":{"0":"elitecreatures:halloween_cosmetics/tex6","1":"elitecreatures:halloween_cosmetics/ani4","particle":"elitecreatures:halloween_cosmetics/tex6"},"elements":[{"from":[8,-3.0407,4.54265],"to":[12,1.9593,4.54265],"rotation":{"angle":0,"axis":"y","origin":[9.5,5.71028,8.89992]},"faces":{"north":{"uv":[6.5,1,4.5,3.5],"texture":"#0"},"east":{"uv":[0,0,0,2.5],"texture":"#0"},"south":{"uv":[4.5,1,6.5,3.5],"texture":"#0"},"west":{"uv":[0,0,0,2.5],"texture":"#0"},"up":{"uv":[0,3,0,0],"rotation":90,"texture":"#0"},"down":{"uv":[0,3,0,0],"rotation":270,"texture":"#0"}}},{"from":[7.25,-11,5.25],"to":[8.75,16,6.75],"rotation":{"angle":0,"axis":"y","origin":[8,18.5,8]},"faces":{"north":{"uv":[3,0.5,3.75,14],"texture":"#0"},"east":{"uv":[0,0.5,0.75,14],"texture":"#0"},"south":{"uv":[3,0.5,3.75,14],"texture":"#0"},"west":{"uv":[0,0.5,0.75,14],"texture":"#0"},"up":{"uv":[14,8,13.25,7.25],"rotation":90,"texture":"#0"},"down":{"uv":[14,8,13.25,7.25],"rotation":90,"texture":"#0"}}},{"from":[4,2,4],"to":[12,13,8],"faces":{"north":{"uv":[4,8.5,8,14],"texture":"#0"},"east":{"uv":[14,3,16,8.5],"texture":"#0"},"south":{"uv":[8,10.5,12,16],"texture":"#0"},"west":{"uv":[14,3,16,8.5],"texture":"#0"},"up":{"uv":[9,1,13,3],"texture":"#0"},"down":{"uv":[8,8.5,12,10.5],"texture":"#0"}}},{"from":[12,9,4],"to":[15,13,8],"faces":{"north":{"uv":[15,10,13.5,12],"texture":"#0"},"east":{"uv":[12,8,14,10],"texture":"#0"},"south":{"uv":[13.5,10,15,12],"texture":"#0"},"west":{"uv":[12,8,14,10],"texture":"#0"},"up":{"uv":[9.25,6.5,10.75,8.5],"texture":"#0"},"down":{"uv":[6.5,14,8,16],"texture":"#0"}}},{"from":[1,9,4],"to":[4,13,8],"rotation":{"angle":0,"axis":"y","origin":[16,0,0]},"faces":{"north":{"uv":[13.5,10,15,12],"texture":"#0"},"east":{"uv":[14,8,12,10],"texture":"#0"},"south":{"uv":[15,10,13.5,12],"texture":"#0"},"west":{"uv":[14,8,12,10],"texture":"#0"},"up":{"uv":[10.75,6.5,9.25,8.5],"texture":"#0"},"down":{"uv":[8,14,6.5,16],"texture":"#0"}}},{"from":[-4,2,4],"to":[0,6,8],"rotation":{"angle":0,"axis":"y","origin":[-3,18.5,4]},"faces":{"north":{"uv":[14,14,12,16],"texture":"#0"},"east":{"uv":[16,12,14,14],"texture":"#0"},"south":{"uv":[14,14,12,16],"texture":"#0"},"west":{"uv":[16,12,14,14],"texture":"#0"},"up":{"uv":[14,16,16,14],"rotation":90,"texture":"#0"},"down":{"uv":[12,14,14,12],"rotation":270,"texture":"#0"}}},{"from":[-5.5,10.25,5.25],"to":[21.5,11.75,6.75],"rotation":{"angle":0,"axis":"y","origin":[4,7.5,6]},"faces":{"north":{"uv":[3,0.5,3.75,14],"rotation":90,"texture":"#0"},"east":{"uv":[14,8,13.25,7.25],"texture":"#0"},"south":{"uv":[3,0.5,3.75,14],"rotation":270,"texture":"#0"},"west":{"uv":[14,8,13.25,7.25],"texture":"#0"},"up":{"uv":[0,0.5,0.75,14],"rotation":270,"texture":"#0"},"down":{"uv":[0,0.5,0.75,14],"rotation":270,"texture":"#0"}}},{"from":[4,-3.0407,7.45735],"to":[8,1.9593,7.45735],"rotation":{"angle":0,"axis":"y","origin":[7.5,5.71028,7.10008]},"faces":{"north":{"uv":[4.5,1,6.5,3.5],"texture":"#0"},"east":{"uv":[0,0,0,2.5],"texture":"#0"},"south":{"uv":[6.5,1,4.5,3.5],"texture":"#0"},"west":{"uv":[0,0,0,2.5],"texture":"#0"},"up":{"uv":[0,0,0,3],"rotation":90,"texture":"#0"},"down":{"uv":[0,0,0,3],"rotation":270,"texture":"#0"}}},{"from":[8,-3.0407,7.45735],"to":[12,1.9593,7.45735],"rotation":{"angle":0,"axis":"y","origin":[9.5,5.71028,7.10008]},"faces":{"north":{"uv":[6.5,1,4.5,3.5],"texture":"#0"},"east":{"uv":[0,0,0,2.5],"texture":"#0"},"south":{"uv":[4.5,1,6.5,3.5],"texture":"#0"},"west":{"uv":[0,0,0,2.5],"texture":"#0"},"up":{"uv":[0,3,0,0],"rotation":90,"texture":"#0"},"down":{"uv":[0,3,0,0],"rotation":270,"texture":"#0"}}},{"from":[4,-3.0407,4.54265],"to":[8,1.9593,4.54265],"rotation":{"angle":0,"axis":"y","origin":[7.5,5.71028,8.89992]},"faces":{"north":{"uv":[4.5,1,6.5,3.5],"texture":"#0"},"east":{"uv":[0,0,0,2.5],"texture":"#0"},"south":{"uv":[6.5,1,4.5,3.5],"texture":"#0"},"west":{"uv":[0,0,0,2.5],"texture":"#0"},"up":{"uv":[0,0,0,3],"rotation":90,"texture":"#0"},"down":{"uv":[0,0,0,3],"rotation":270,"texture":"#0"}}},{"from":[-4.1,3.75,4.75],"to":[-4.1,12.25,7.25],"faces":{"north":{"uv":[0,0,0,4.25],"texture":"#0"},"east":{"uv":[12,4.25,10.75,8.5],"texture":"#0"},"south":{"uv":[0,0,0,4.25],"texture":"#0"},"west":{"uv":[10.75,4.25,12,8.5],"texture":"#0"},"up":{"uv":[0,0,0,1.25],"texture":"#0"},"down":{"uv":[0,0,0,1.25],"texture":"#0"}}},{"from":[0.1,3.75,4.75],"to":[0.1,12.25,7.25],"rotation":{"angle":0,"axis":"y","origin":[16,0,0]},"faces":{"north":{"uv":[0,0,0,4.25],"texture":"#0"},"east":{"uv":[12,4.25,10.75,8.5],"texture":"#0"},"south":{"uv":[0,0,0,4.25],"texture":"#0"},"west":{"uv":[10.75,4.25,12,8.5],"texture":"#0"},"up":{"uv":[0,0,0,1.25],"texture":"#0"},"down":{"uv":[0,0,0,1.25],"texture":"#0"}}},{"from":[15.9,3.75,4.75],"to":[15.9,12.25,7.25],"faces":{"north":{"uv":[0,0,0,4.25],"texture":"#0"},"east":{"uv":[12,4.25,10.75,8.5],"texture":"#0"},"south":{"uv":[0,0,0,4.25],"texture":"#0"},"west":{"uv":[10.75,4.25,12,8.5],"texture":"#0"},"up":{"uv":[0,0,0,1.25],"texture":"#0"},"down":{"uv":[0,0,0,1.25],"texture":"#0"}}},{"from":[20.1,3.75,4.75],"to":[20.1,12.25,7.25],"rotation":{"angle":0,"axis":"y","origin":[16,0,0]},"faces":{"north":{"uv":[0,0,0,4.25],"texture":"#0"},"east":{"uv":[12,4.25,10.75,8.5],"texture":"#0"},"south":{"uv":[0,0,0,4.25],"texture":"#0"},"west":{"uv":[10.75,4.25,12,8.5],"texture":"#0"},"up":{"uv":[0,0,0,1.25],"texture":"#0"},"down":{"uv":[0,0,0,1.25],"texture":"#0"}}},{"from":[16,2,4],"to":[20,6,8],"rotation":{"angle":0,"axis":"y","origin":[19,18.5,4]},"faces":{"north":{"uv":[12,14,14,16],"texture":"#0"},"east":{"uv":[14,12,16,14],"texture":"#0"},"south":{"uv":[12,14,14,16],"texture":"#0"},"west":{"uv":[14,12,16,14],"texture":"#0"},"up":{"uv":[14,14,16,16],"rotation":90,"texture":"#0"},"down":{"uv":[12,12,14,14],"rotation":270,"texture":"#0"}}},{"from":[-4.75,5,5.5],"to":[0.25,12,5.5],"faces":{"north":{"uv":[6,2.5,11,9.5],"texture":"#1"},"east":{"uv":[0,0,0,0.625],"texture":"#1"},"south":{"uv":[11,2.5,6,9.5],"texture":"#1"},"west":{"uv":[0,0,0,0.625],"texture":"#1"},"up":{"uv":[0,0,0.625,0],"texture":"#1"},"down":{"uv":[0,0,0.625,0],"texture":"#1"}}},{"from":[15.75,5,5.5],"to":[20.75,12,5.5],"rotation":{"angle":0,"axis":"y","origin":[16,0,0]},"faces":{"north":{"uv":[11,2.5,6,9.5],"texture":"#1"},"east":{"uv":[0,0,0,0.625],"texture":"#1"},"south":{"uv":[6,2.5,11,9.5],"texture":"#1"},"west":{"uv":[0,0,0,0.625],"texture":"#1"},"up":{"uv":[0.625,0,0,0],"texture":"#1"},"down":{"uv":[0.625,0,0,0],"texture":"#1"}}}],"gui_light":"front","display":{"thirdperson_righthand":{"rotation":[54,17,0],"translation":[-1,0,0],"scale":[0.4,0.4,0.4]},"thirdperson_lefthand":{"rotation":[67.5,180,0],"translation":[-5.75,-5.25,8.25]},"firstperson_righthand":{"rotation":[0,120,0],"translation":[0,5,0],"scale":[0.59922,0.59922,0.59922]},"firstperson_lefthand":{"rotation":[0,120,0],"translation":[0,2,0],"scale":[0,0,0]},"ground":{"rotation":[41.42,0.32,-8.1],"translation":[0,4,0],"scale":[0.5,0.5,0.5]},"gui":{"rotation":[11,135,0],"translation":[0.5,3,0],"scale":[0.51,0.51,0.51]},"head":{"rotation":[0,180,0],"translation":[0,-70,2.5],"scale":[1.6,1.6,1.6]},"fixed":{"translation":[0,5.5,0],"scale":[1.55469,1.55469,1.55469]}},"groups":[{"name":"group","origin":[16,0,0],"color":0,"children":[0,1,2,3,4,5,6,7,8,9,10,11,12,13,14,15,16]}]}